LICENSE.txt
README.md
setup.cfg
setup.py
sql_docopt_queries.egg-info/PKG-INFO
sql_docopt_queries.egg-info/SOURCES.txt
sql_docopt_queries.egg-info/dependency_links.txt
sql_docopt_queries.egg-info/requires.txt
sql_docopt_queries.egg-info/top_level.txt
sql_queries/__init__.py
sql_queries/db_utility.py