Metadata-Version: 2.1
Name: sql-docopt-queries
Version: 0.0.4
Summary: sqlite interface
Home-page: https://github.com/dn757657/sql-queries.git
Author: Dan
Author-email: daniel.js.campbell@gmail.com
License: MIT
Download-URL: https://github.com/dn757657/sql-queries/archive/refs/tags/0.0.4.tar.gz
Keywords: docopt,sqlite,ct-finance
Platform: UNKNOWN
Classifier: Development Status :: 3 - Alpha
Classifier: Intended Audience :: Developers
Classifier: Topic :: Software Development :: Build Tools
Classifier: License :: OSI Approved :: MIT License
Classifier: Programming Language :: Python :: 3
Classifier: Programming Language :: Python :: 3.4
Classifier: Programming Language :: Python :: 3.5
Classifier: Programming Language :: Python :: 3.6
License-File: LICENSE.txt
